{
 "absolute_value": 0,
 "align_labels_right": 0,
 "creation": "2024-06-28 17:08:58.551715",
 "css": "\n.print-format td{\n    padding: 5px !important;\n}\n\n.print-format th {\n    padding: 5px !important;\n}\n",
 "custom_format": 0,
 "default_print_language": "en",
 "disabled": 0,
 "doc_type": "Purchase Order",
 "docstatus": 0,
 "doctype": "Print Format",
 "font_size": 14,
 "format_data": "[{\"fieldname\": \"print_heading_template\", \"fieldtype\": \"Custom HTML\", \"options\": \"<div class=\\\"print-heading\\\"></div>\"}, {\"fieldtype\": \"Section Break\", \"label\": \"\"}, {\"fieldtype\": \"Column Break\"}, {\"fieldname\": \"_custom_html\", \"print_hide\": 0, \"label\": \"Custom HTML\", \"fieldtype\": \"HTML\", \"options\": \"<table border=\\\"1\\\" class=\\\"col-xs-12\\\" style=\\\"line-height: normal;\\\">\\n    <tr>\\n    <th colspan=4 class=\\\"text-center\\\" style=\\\"color: #74808b; font-weight: normal; border-bottom-width: 1px !important;\\\">\\n        <b>PURCHASE ORDER</b></th>\\n    </tr>\\n    <tr style=\\\"font-size: 12px;\\\">\\n        <td class=\\\"col-xs-2\\\">NO.</td>\\n        <td class=\\\"col-xs-4\\\">{{doc.name}}</td>\\n        <td class=\\\"col-xs-2\\\">DATE</td>\\n        <td class=\\\"col-xs-4\\\">{{ frappe.utils.formatdate(doc.get_formatted('transaction_date'), \\\"dd-MM-yyyy\\\") }}</td>\\n        \\n    </tr>\\n    <tr style=\\\"font-size: 12px;\\\">\\n        <td colspan=2 class=\\\"col-xs-6 text-center\\\">Details of Supplier</td>\\n        <td colspan=2 class=\\\"col-xs-6 text-center\\\">Details of Receiver/Consignee</td>\\n    </tr>\\n    <tr style=\\\"font-size: 12px;\\\">\\n        <td>Name</td>\\n        <td><b>{{doc.supplier_name}}</b></td>\\n        <td>Name</td>\\n        <td><b>Kalinga International Coal Terminal Paradip Pvt. Ltd.</b></td>\\n    </tr>\\n    <tr style=\\\"font-size: 12px;\\\">\\n        <td>Address</td>\\n        <td>{{doc.address_display or \\\"\\\"}}</td>\\n        <td rowspan=2>Address</td>\\n        <td rowspan=2>{{doc.billing_address_display or \\\"\\\"}}</td>\\n    </tr>\\n    <tr style=\\\"font-size: 12px;\\\">\\n        <td>GSTIN</td>\\n        <td>{{doc.supplier_gstin or \\\"\\\"}}</td>\\n    </tr>\\n    <tr style=\\\"font-size: 12px;\\\">\\n        <td>Kind Attn.</td>\\n        <td>{{doc.contact_display or \\\"\\\"}}</td>\\n        <td>GSTIN</td>\\n        <td>{{doc.company_gstin or \\\"\\\"}}</td>\\n    </tr>\\n    <tr style=\\\"font-size: 12px;\\\">\\n        {% set company=frappe.db.get_list('Company',\\n        filters={\\\"name\\\":doc.company},fields=['name','pan','custom_cin_no']) %}\\n        <td>Mobile No.</td>\\n        <td>{{doc.contact_mobile or \\\"\\\"}}</td>\\n        <td>Pan No.</td>\\n        <td>{{company[0].pan or \\\"\\\"}}</td>\\n    </tr>\\n    <tr style=\\\"font-size: 12px;\\\">\\n        <td>Email_id</td>\\n        <td>{{doc.contact_email or \\\"\\\"}}</td>\\n        <td>CIN</td>\\n        <td>{{company[0].custom_cin_no or \\\"\\\"}}</td>\\n    </tr>\\n    <tr style=\\\"font-size: 12px;\\\">\\n        {% set i = doc.items %}\\n        <td>Subject</td>\\n        <td colspan=3>\\n        {% set item_groups = [] %}\\n            {% for item in doc.items %}\\n\\t           {% set item_group = frappe.db.get_value('Item', item.item_code, 'item_group') %}\\n\\t\\t        {{ item_groups.append(item_group) or ''}}\\n\\t        {% endfor %}\\t\\n\\t\\n\\t{% set unique_item_groups = item_groups|unique|list %}\\n\\n\\t{% set grp = unique_item_groups |join(', ') %}\\n            Purchase Order for Supply of {{ grp }}</td>\\n    </tr>\\n    <tr style=\\\"font-size: 12px;\\\">\\n        <td>Reference</td>\\n        {% set q=frappe.db.get_list('Supplier Quotation', filters={\\\"name\\\":i[0].supplier_quotation},fields=['quotation_number','transaction_date']) %}\\n        {% if q | length > 0 %}\\n        \\n        <td colspan=3>Your Quotation No. {{q[0].quotation_number or \\\"\\\"}} dated on  {{ frappe.utils.formatdate(q[0].transaction_date.strftime(\\\"%d-%m-%Y\\\")) }} </td>\\n        {% else %}\\n        <td colspan=3>Your Quotation No. - dated on - </td>\\n        {% endif %}\\n    </tr>\\n    <tr style=\\\"font-size: 12px;\\\">\\n        <td>Acceptance</td>\\n        <td colspan=3>Referring to the above subject, our company is pleased to place Purchase Order on you under the following terms & conditions.</td>\\n    </tr>\\n    \\n</table>\\n<br>\"}, {\"fieldtype\": \"Section Break\", \"label\": \"\"}, {\"fieldtype\": \"Column Break\"}, {\"fieldname\": \"_custom_html\", \"print_hide\": 0, \"label\": \"Custom HTML\", \"fieldtype\": \"HTML\", \"options\": \"<table border=\\\"1\\\" class=\\\"col-xs-12 ql-snow\\\" style=\\\"line-height: normal; min-width:100%; font-size: 12px\\\">\\n    <tr>\\n        <td><b>SI No</b></td>\\n        <td><b>Material Description</b></td>\\n        <td><b>Make</b></td>\\n        <td><b>Qty.</b></td>\\n        <td><b>Uom</b></td>\\n        <td><b>Rate</b></td>\\n        <td><b>Amount</b></td>\\n    </tr>\\n     {% for i in doc.items %}\\n    <tr>\\n        <td>{{i.idx or \\\"\\\"}}</td>\\n        <td>{{i.description or \\\"\\\"}}</td>\\n        <td>{{i.brand or \\\"\\\"}}</td>\\n        <td>{{i.qty or \\\"\\\"}}</td>\\n        <td>{{i.uom or \\\"\\\"}}</td>\\n        <td>{{i.rate or \\\"\\\"}}</td>\\n        <td>{{i.amount or \\\"\\\"}}</td>\\n    </tr>\\n    {% endfor %}\\n    <tr>\\n        <td colspan=5 rowspan=3 class=\\\"text-center\\\"><b>{{doc.in_words or \\\"\\\"}}</b></td>\\n        <td>Sub Total</td>\\n        <td>{{doc.total or \\\"\\\"}}</td>\\n    </tr>\\n    <tr>\\n        <td>Taxes and Charges</td>\\n        <td>{{doc.total_taxes_and_charges or \\\"\\\"}}</td>\\n    </tr>\\n    <tr>\\n        <td><b>Grand Total</b></td>\\n        <td><b>{{doc.rounded_total or \\\"\\\"}}</b></td>\\n    </tr>\\n</table>\"}, {\"fieldname\": \"_custom_html\", \"print_hide\": 0, \"label\": \"Custom HTML\", \"fieldtype\": \"HTML\", \"options\": \"<div class=\\\"col-sm-12 ql-snow\\\" style=\\\"font-size: 12px\\\">\\n    {{doc.gst_breakup_table}}\\n</div>\\n<h4 class=\\\"text-center\\\">Terms & Conditions</h4>\\n<div class=\\\"ql-snow\\\" style=\\\"font-size: 12px;\\\">\\n    {{doc.terms}}\\n</div>\"}, {\"fieldname\": \"_custom_html\", \"print_hide\": 0, \"label\": \"Custom HTML\", \"fieldtype\": \"HTML\", \"options\": \"<table border=\\\"1\\\" class=\\\"col-sm-12\\\" style=\\\"min-width:100%; font-size: 12px;\\\">\\n    <tr>\\n        <td>Unconditionally accepted for and on behalf of :</td>\\n        <td rowspan='2' class=\\\"text-center\\\"><b>{{doc.company}}</b></td>\\n    </tr>\\n    <tr>\\n        <td class=\\\"text-center\\\"><b>{{doc.supplier_name}}</b></td>\\n    </tr>\\n    \\n    <tr>\\n        <td class=\\\"col-sm-6\\\" style=\\\"height: 100px\\\"></td>\\n        <td class=\\\"col-sm-6\\\" style=\\\"height: 100px\\\"></td>\\n    </tr>\\n    <tr>\\n        <td class=\\\"col-sm-6\\\">(Acceptance as per General Terms & Conditions)</td>\\n        <td class=\\\"col-sm-6\\\"><b>Authorized Signatory</b></td>\\n    </tr>\\n</table>\"}]",
 "idx": 0,
 "line_breaks": 0,
 "margin_bottom": 15.0,
 "margin_left": 15.0,
 "margin_right": 15.0,
 "margin_top": 15.0,
 "modified": "2024-06-28 17:08:58.551715",
 "modified_by": "Administrator",
 "module": "Kict",
 "name": "Coal-PO",
 "owner": "Administrator",
 "page_number": "Hide",
 "print_designer": 0,
 "print_designer_template_app": "print_designer",
 "print_format_builder": 0,
 "print_format_builder_beta": 0,
 "print_format_type": "Jinja",
 "raw_printing": 0,
 "show_section_headings": 0,
 "standard": "Yes"
}